MANIFEST.in
README.md
setup.cfg
setup.py
JPlot/__init__.py
JPlot/ax.py
JPlot/figure.py
JPlot/pyplot.py
JPlot/pyplotAux.py
JPlot.egg-info/PKG-INFO
JPlot.egg-info/SOURCES.txt
JPlot.egg-info/dependency_links.txt
JPlot.egg-info/requires.txt
JPlot.egg-info/top_level.txt
JPlot/const/__init__.py
JPlot/const/color.py
JPlot/const/const.py
JPlot/styles/JStyle
JPlot/styles/__init__.py
JPlot/styles/fourcol
JPlot/styles/largeFont
JPlot/styles/onecol
JPlot/styles/onecolLargeFont
JPlot/styles/presentation
JPlot/styles/publication
JPlot/styles/twocol