Metadata-Version: 1.1
Name: JPlot
Version: 0.0.13
Summary: A Python library for generating publication ready figures
Home-page: https://github.com/1a1a11a/JPlot
Author: Juncheng Yang
Author-email: juncheny@cs.cmu.edu
License: MIT
Keywords: plot,easy
Platform: UNKNOWN
Classifier: Development Status :: 3 - Alpha
Classifier: Programming Language :: Python :: 3
Classifier: Programming Language :: Python :: 3.4
Classifier: Programming Language :: Python :: 3.5
Classifier: Programming Language :: Python :: 3.6
Classifier: Programming Language :: Python :: 3.7
Classifier: Programming Language :: Python :: 3.8
Requires: matplotlib
Requires: numpy
